ccy_dynamic_image/__init__.py
ccy_dynamic_image/converter.py
ccy_dynamic_image-0.3.dist-info/LICENSE
ccy_dynamic_image-0.3.dist-info/METADATA
ccy_dynamic_image-0.3.dist-info/WHEEL
ccy_dynamic_image-0.3.dist-info/entry_points.txt
ccy_dynamic_image-0.3.dist-info/top_level.txt
ccy_dynamic_image-0.3.dist-info/RECORD
