Metadata-Version: 2.1
Name: ccy-dynamic-image
Version: 0.3
Summary: add dynamic effect to text or image
Home-page: https://github.com/tenderzada/ccy_dynamic_images
Author: Chen Jiao
Author-email: chenjiao@mail.ynu.edu.com
License: UNKNOWN
Platform: UNKNOWN
Classifier: Programming Language :: Python :: 3
Classifier: License :: OSI Approved :: MIT License
Classifier: Operating System :: OS Independent
Requires-Dist: Pillow (>=7.0.0)
Requires-Dist: numpy (==1.16.2)
